trueapi/__init__.py
truecli-0.0.1.dist-info/LICENSE
truecli-0.0.1.dist-info/METADATA
truecli-0.0.1.dist-info/WHEEL
truecli-0.0.1.dist-info/top_level.txt
truecli-0.0.1.dist-info/RECORD
